xscaffold/__init__.py
xscaffold/xscaffold.py
xscaffold-1.2.0.dist-info/LICENSE
xscaffold-1.2.0.dist-info/METADATA
xscaffold-1.2.0.dist-info/WHEEL
xscaffold-1.2.0.dist-info/entry_points.txt
xscaffold-1.2.0.dist-info/top_level.txt
xscaffold-1.2.0.dist-info/RECORD
